[
    [
        {
            "exchangedate": "07.10.2025",
            "r030": 12,
            "cc": "DZD",
            "txt": "Алжирський динар",
            "enname": "Algerian Dinar",
            "rate": 3.1927,
            "units": 10,
            "rate_per_unit": 0.31927,
            "group": "1",
            "calcdate": "06.10.2025"
        },
        {
            "exchangedate": "08.10.2025",
            "r030": 12,
            "cc": "DZD",
            "txt": "Алжирський динар",
            "enname": "Algerian Dinar",
            "rate": 3.1888,
            "units": 10,
            "rate_per_unit": 0.31888,
            "group": "1",
            "calcdate": "07.10.2025"
        },
        {
            "exchangedate": "07.10.2025",
            "r030": 36,
            "cc": "AUD",
            "txt": "Австралійський долар",
            "enname": "Australian Dollar",
            "rate": 27.2767,
            "units": 1,
            "rate_per_unit": 27.2767,
            "group": "1",
            "calcdate": "06.10.2025"
        },
        {
            "exchangedate": "08.10.2025",
            "r030": 36,
            "cc": "AUD",
            "txt": "Австралійський долар",
            "enname": "Australian Dollar",
            "rate": 27.2106,
            "units": 1,
            "rate_per_unit": 27.2106,
            "group": "1",
            "calcdate": "07.10.2025"
        },
        {
            "exchangedate": "08.10.2025",
            "r030": 50,
            "cc": "BDT",
            "txt": "Така",
            "enname": "Taka",
            "rate": 3.3986,
            "units": 10,
            "rate_per_unit": 0.33986,
            "group": "1",
            "calcdate": "07.10.2025"
        },
        {
            "exchangedate": "07.10.2025",
            "r030": 50,
            "cc": "BDT",
            "txt": "Така",
            "enname": "Taka",
            "rate": 3.4064,
            "units": 10,
            "rate_per_unit": 0.34064,
            "group": "1",
            "calcdate": "06.10.2025"
        },
        {
            "exchangedate": "07.10.2025",
            "r030": 124,
            "cc": "CAD",
            "txt": "Канадський долар",
            "enname": "Canadian Dollar",
            "rate": 29.6096,
            "units": 1,
            "rate_per_unit": 29.6096,
            "group": "1",
            "calcdate": "06.10.2025"
        },
        {
            "exchangedate": "08.10.2025",
            "r030": 124,
            "cc": "CAD",
            "txt": "Канадський долар",
            "enname": "Canadian Dollar",
            "rate": 29.598,
            "units": 1,
            "rate_per_unit": 29.598,
            "group": "1",
            "calcdate": "07.10.2025"
        },
        {
            "exchangedate": "08.10.2025",
            "r030": 156,
            "cc": "CNY",
            "txt": "Юань Женьміньбі",
            "enname": "Yuan Renminbi ",
            "rate": 5.8018,
            "units": 1,
            "rate_per_unit": 5.8018,
            "group": "1",
            "calcdate": "07.10.2025"
        },
        {
            "exchangedate": "07.10.2025",
            "r030": 156,
            "cc": "CNY",
            "txt": "Юань Женьміньбі",
            "enname": "Yuan Renminbi ",
            "rate": 5.8053,
            "units": 1,
            "rate_per_unit": 5.8053,
            "group": "1",
            "calcdate": "06.10.2025"
        },
        {
            "exchangedate": "08.10.2025",
            "r030": 203,
            "cc": "CZK",
            "txt": "Чеська крона",
            "enname": "Czech Koruna",
            "rate": 1.981,
            "units": 1,
            "rate_per_unit": 1.981,
            "group": "1",
            "calcdate": "07.10.2025"
        },
        {
            "exchangedate": "07.10.2025",
            "r030": 203,
            "cc": "CZK",
            "txt": "Чеська крона",
            "enname": "Czech Koruna",
            "rate": 1.9863,
            "units": 1,
            "rate_per_unit": 1.9863,
            "group": "1",
            "calcdate": "06.10.2025"
        },
        {
            "exchangedate": "08.10.2025",
            "r030": 208,
            "cc": "DKK",
            "txt": "Данська крона",
            "enname": "Danish Krone",
            "rate": 6.4526,
            "units": 1,
            "rate_per_unit": 6.4526,
            "group": "1",
            "calcdate": "07.10.2025"
        },
        {
            "exchangedate": "07.10.2025",
            "r030": 208,
            "cc": "DKK",
            "txt": "Данська крона",
            "enname": "Danish Krone",
            "rate": 6.4647,
            "units": 1,
            "rate_per_unit": 6.4647,
            "group": "1",
            "calcdate": "06.10.2025"
        },
        {
            "exchangedate": "07.10.2025",
            "r030": 344,
            "cc": "HKD",
            "txt": "Гонконгівський долар",
            "enname": "Hong Kong Dollar",
            "rate": 5.3113,
            "units": 1,
            "rate_per_unit": 5.3113,
            "group": "1",
            "calcdate": "06.10.2025"
        },
        {
            "exchangedate": "08.10.2025",
            "r030": 344,
            "cc": "HKD",
            "txt": "Гонконгівський долар",
            "enname": "Hong Kong Dollar",
            "rate": 5.3084,
            "units": 1,
            "rate_per_unit": 5.3084,
            "group": "1",
            "calcdate": "07.10.2025"
        },
        {
            "exchangedate": "07.10.2025",
            "r030": 348,
            "cc": "HUF",
            "txt": "Форинт",
            "enname": "Forint",
            "rate": 12.4013,
            "units": 100,
            "rate_per_unit": 0.124013,
            "group": "1",
            "calcdate": "06.10.2025"
        },
        {
            "exchangedate": "08.10.2025",
            "r030": 348,
            "cc": "HUF",
            "txt": "Форинт",
            "enname": "Forint",
            "rate": 12.2821,
            "units": 100,
            "rate_per_unit": 0.122821,
            "group": "1",
            "calcdate": "07.10.2025"
        },
        {
            "exchangedate": "07.10.2025",
            "r030": 356,
            "cc": "INR",
            "txt": "Індійська рупія",
            "enname": "Indian Rupee",
            "rate": 4.656,
            "units": 10,
            "rate_per_unit": 0.4656,
            "group": "1",
            "calcdate": "06.10.2025"
        },
        {
            "exchangedate": "08.10.2025",
            "r030": 356,
            "cc": "INR",
            "txt": "Індійська рупія",
            "enname": "Indian Rupee",
            "rate": 4.6536,
            "units": 10,
            "rate_per_unit": 0.46536,
            "group": "1",
            "calcdate": "07.10.2025"
        },
        {
            "exchangedate": "08.10.2025",
            "r030": 360,
            "cc": "IDR",
            "txt": "Рупія",
            "enname": "Rupiah",
            "rate": 2.496,
            "units": 1000,
            "rate_per_unit": 0.002496,
            "group": "1",
            "calcdate": "07.10.2025"
        },
        {
            "exchangedate": "07.10.2025",
            "r030": 360,
            "cc": "IDR",
            "txt": "Рупія",
            "enname": "Rupiah",
            "rate": 2.4931,
            "units": 1000,
            "rate_per_unit": 0.0024931,
            "group": "1",
            "calcdate": "06.10.2025"
        },
        {
            "exchangedate": "08.10.2025",
            "r030": 376,
            "cc": "ILS",
            "txt": "Новий ізраїльський шекель",
            "enname": "New Israeli Sheqel",
            "rate": 12.6101,
            "units": 1,
            "rate_per_unit": 12.6101,
            "group": "1",
            "calcdate": "07.10.2025"
        },
        {
            "exchangedate": "07.10.2025",
            "r030": 376,
            "cc": "ILS",
            "txt": "Новий ізраїльський шекель",
            "enname": "New Israeli Sheqel",
            "rate": 12.6078,
            "units": 1,
            "rate_per_unit": 12.6078,
            "group": "1",
            "calcdate": "06.10.2025"
        },
        {
            "exchangedate": "08.10.2025",
            "r030": 392,
            "cc": "JPY",
            "txt": "Єна",
            "enname": "Yen",
            "rate": 2.738,
            "units": 10,
            "rate_per_unit": 0.2738,
            "group": "1",
            "calcdate": "07.10.2025"
        },
        {
            "exchangedate": "07.10.2025",
            "r030": 392,
            "cc": "JPY",
            "txt": "Єна",
            "enname": "Yen",
            "rate": 2.7495,
            "units": 10,
            "rate_per_unit": 0.27495,
            "group": "1",
            "calcdate": "06.10.2025"
        },
        {
            "exchangedate": "07.10.2025",
            "r030": 398,
            "cc": "KZT",
            "txt": "Теньге",
            "enname": "Tenge",
            "rate": 7.6035,
            "units": 100,
            "rate_per_unit": 0.076035,
            "group": "1",
            "calcdate": "06.10.2025"
        },
        {
            "exchangedate": "08.10.2025",
            "r030": 398,
            "cc": "KZT",
            "txt": "Теньге",
            "enname": "Tenge",
            "rate": 7.6347,
            "units": 100,
            "rate_per_unit": 0.076347,
            "group": "1",
            "calcdate": "07.10.2025"
        },
        {
            "exchangedate": "08.10.2025",
            "r030": 410,
            "cc": "KRW",
            "txt": "Вона",
            "enname": "Won",
            "rate": 2.9233,
            "units": 100,
            "rate_per_unit": 0.029233,
            "group": "1",
            "calcdate": "07.10.2025"
        },
        {
            "exchangedate": "07.10.2025",
            "r030": 410,
            "cc": "KRW",
            "txt": "Вона",
            "enname": "Won",
            "rate": 2.927,
            "units": 100,
            "rate_per_unit": 0.02927,
            "group": "1",
            "calcdate": "06.10.2025"
        },
        {
            "exchangedate": "07.10.2025",
            "r030": 422,
            "cc": "LBP",
            "txt": "Ліванський фунт",
            "enname": "Lebanese Pound",
            "rate": 0.0462,
            "units": 100,
            "rate_per_unit": 0.000462,
            "group": "1",
            "calcdate": "06.10.2025"
        },
        {
            "exchangedate": "08.10.2025",
            "r030": 422,
            "cc": "LBP",
            "txt": "Ліванський фунт",
            "enname": "Lebanese Pound",
            "rate": 0.0461,
            "units": 100,
            "rate_per_unit": 0.000461,
            "group": "1",
            "calcdate": "07.10.2025"
        },
        {
            "exchangedate": "07.10.2025",
            "r030": 458,
            "cc": "MYR",
            "txt": "Малайзійський ринггіт",
            "enname": "Malaysian Ringgit",
            "rate": 9.8073,
            "units": 1,
            "rate_per_unit": 9.8073,
            "group": "1",
            "calcdate": "06.10.2025"
        },
        {
            "exchangedate": "08.10.2025",
            "r030": 458,
            "cc": "MYR",
            "txt": "Малайзійський ринггіт",
            "enname": "Malaysian Ringgit",
            "rate": 9.8039,
            "units": 1,
            "rate_per_unit": 9.8039,
            "group": "1",
            "calcdate": "07.10.2025"
        },
        {
            "exchangedate": "07.10.2025",
            "r030": 484,
            "cc": "MXN",
            "txt": "Мексиканське песо",
            "enname": "Mexican Peso",
            "rate": 2.2428,
            "units": 1,
            "rate_per_unit": 2.2428,
            "group": "1",
            "calcdate": "06.10.2025"
        },
        {
            "exchangedate": "08.10.2025",
            "r030": 484,
            "cc": "MXN",
            "txt": "Мексиканське песо",
            "enname": "Mexican Peso",
            "rate": 2.2475,
            "units": 1,
            "rate_per_unit": 2.2475,
            "group": "1",
            "calcdate": "07.10.2025"
        },
        {
            "exchangedate": "08.10.2025",
            "r030": 498,
            "cc": "MDL",
            "txt": "Молдовський лей",
            "enname": "Moldovan Leu",
            "rate": 2.4782,
            "units": 1,
            "rate_per_unit": 2.4782,
            "group": "1",
            "calcdate": "07.10.2025"
        },
        {
            "exchangedate": "07.10.2025",
            "r030": 498,
            "cc": "MDL",
            "txt": "Молдовський лей",
            "enname": "Moldovan Leu",
            "rate": 2.4763,
            "units": 1,
            "rate_per_unit": 2.4763,
            "group": "1",
            "calcdate": "06.10.2025"
        },
        {
            "exchangedate": "07.10.2025",
            "r030": 554,
            "cc": "NZD",
            "txt": "Новозеландський долар",
            "enname": "New Zealand Dollar",
            "rate": 24.0625,
            "units": 1,
            "rate_per_unit": 24.0625,
            "group": "1",
            "calcdate": "06.10.2025"
        },
        {
            "exchangedate": "08.10.2025",
            "r030": 554,
            "cc": "NZD",
            "txt": "Новозеландський долар",
            "enname": "New Zealand Dollar",
            "rate": 23.9859,
            "units": 1,
            "rate_per_unit": 23.9859,
            "group": "1",
            "calcdate": "07.10.2025"
        },
        {
            "exchangedate": "08.10.2025",
            "r030": 578,
            "cc": "NOK",
            "txt": "Норвезька крона",
            "enname": "Norwegian Krone",
            "rate": 4.1508,
            "units": 1,
            "rate_per_unit": 4.1508,
            "group": "1",
            "calcdate": "07.10.2025"
        },
        {
            "exchangedate": "07.10.2025",
            "r030": 578,
            "cc": "NOK",
            "txt": "Норвезька крона",
            "enname": "Norwegian Krone",
            "rate": 4.1507,
            "units": 1,
            "rate_per_unit": 4.1507,
            "group": "1",
            "calcdate": "06.10.2025"
        },
        {
            "exchangedate": "08.10.2025",
            "r030": 682,
            "cc": "SAR",
            "txt": "Саудівський ріял",
            "enname": "Saudi Riyal",
            "rate": 11.0143,
            "units": 1,
            "rate_per_unit": 11.0143,
            "group": "1",
            "calcdate": "07.10.2025"
        },
        {
            "exchangedate": "07.10.2025",
            "r030": 682,
            "cc": "SAR",
            "txt": "Саудівський ріял",
            "enname": "Saudi Riyal",
            "rate": 11.0225,
            "units": 1,
            "rate_per_unit": 11.0225,
            "group": "1",
            "calcdate": "06.10.2025"
        },
        {
            "exchangedate": "08.10.2025",
            "r030": 702,
            "cc": "SGD",
            "txt": "Сінгапурський долар",
            "enname": "Singapore Dollar",
            "rate": 31.946,
            "units": 1,
            "rate_per_unit": 31.946,
            "group": "1",
            "calcdate": "07.10.2025"
        },
        {
            "exchangedate": "07.10.2025",
            "r030": 702,
            "cc": "SGD",
            "txt": "Сінгапурський долар",
            "enname": "Singapore Dollar",
            "rate": 31.9556,
            "units": 1,
            "rate_per_unit": 31.9556,
            "group": "1",
            "calcdate": "06.10.2025"
        },
        {
            "exchangedate": "08.10.2025",
            "r030": 704,
            "cc": "VND",
            "txt": "Донг",
            "enname": "Dong",
            "rate": 1.567,
            "units": 1000,
            "rate_per_unit": 0.001567,
            "group": "1",
            "calcdate": "07.10.2025"
        },
        {
            "exchangedate": "07.10.2025",
            "r030": 704,
            "cc": "VND",
            "txt": "Донг",
            "enname": "Dong",
            "rate": 1.5678,
            "units": 1000,
            "rate_per_unit": 0.0015678,
            "group": "1",
            "calcdate": "06.10.2025"
        },
        {
            "exchangedate": "08.10.2025",
            "r030": 710,
            "cc": "ZAR",
            "txt": "Ренд",
            "enname": "Rand",
            "rate": 2.4005,
            "units": 1,
            "rate_per_unit": 2.4005,
            "group": "1",
            "calcdate": "07.10.2025"
        },
        {
            "exchangedate": "07.10.2025",
            "r030": 710,
            "cc": "ZAR",
            "txt": "Ренд",
            "enname": "Rand",
            "rate": 2.3964,
            "units": 1,
            "rate_per_unit": 2.3964,
            "group": "1",
            "calcdate": "06.10.2025"
        },
        {
            "exchangedate": "08.10.2025",
            "r030": 752,
            "cc": "SEK",
            "txt": "Шведська крона",
            "enname": "Swedish Krona",
            "rate": 4.3986,
            "units": 1,
            "rate_per_unit": 4.3986,
            "group": "1",
            "calcdate": "07.10.2025"
        },
        {
            "exchangedate": "07.10.2025",
            "r030": 752,
            "cc": "SEK",
            "txt": "Шведська крона",
            "enname": "Swedish Krona",
            "rate": 4.3942,
            "units": 1,
            "rate_per_unit": 4.3942,
            "group": "1",
            "calcdate": "06.10.2025"
        },
        {
            "exchangedate": "07.10.2025",
            "r030": 756,
            "cc": "CHF",
            "txt": "Швейцарський франк",
            "enname": "Swiss Franc",
            "rate": 51.8121,
            "units": 1,
            "rate_per_unit": 51.8121,
            "group": "1",
            "calcdate": "06.10.2025"
        },
        {
            "exchangedate": "08.10.2025",
            "r030": 756,
            "cc": "CHF",
            "txt": "Швейцарський франк",
            "enname": "Swiss Franc",
            "rate": 51.7288,
            "units": 1,
            "rate_per_unit": 51.7288,
            "group": "1",
            "calcdate": "07.10.2025"
        },
        {
            "exchangedate": "07.10.2025",
            "r030": 764,
            "cc": "THB",
            "txt": "Бат",
            "enname": "Baht",
            "rate": 12.7434,
            "units": 10,
            "rate_per_unit": 1.27434,
            "group": "1",
            "calcdate": "06.10.2025"
        },
        {
            "exchangedate": "08.10.2025",
            "r030": 764,
            "cc": "THB",
            "txt": "Бат",
            "enname": "Baht",
            "rate": 12.7063,
            "units": 10,
            "rate_per_unit": 1.27063,
            "group": "1",
            "calcdate": "07.10.2025"
        },
        {
            "exchangedate": "08.10.2025",
            "r030": 784,
            "cc": "AED",
            "txt": "Дирхам ОАЕ",
            "enname": "UAE Dirham",
            "rate": 11.2485,
            "units": 1,
            "rate_per_unit": 11.2485,
            "group": "1",
            "calcdate": "07.10.2025"
        },
        {
            "exchangedate": "07.10.2025",
            "r030": 784,
            "cc": "AED",
            "txt": "Дирхам ОАЕ",
            "enname": "UAE Dirham",
            "rate": 11.2553,
            "units": 1,
            "rate_per_unit": 11.2553,
            "group": "1",
            "calcdate": "06.10.2025"
        },
        {
            "exchangedate": "07.10.2025",
            "r030": 788,
            "cc": "TND",
            "txt": "Туніський динар",
            "enname": "Tunisian Dinar",
            "rate": 14.1603,
            "units": 1,
            "rate_per_unit": 14.1603,
            "group": "1",
            "calcdate": "06.10.2025"
        },
        {
            "exchangedate": "08.10.2025",
            "r030": 788,
            "cc": "TND",
            "txt": "Туніський динар",
            "enname": "Tunisian Dinar",
            "rate": 14.1425,
            "units": 1,
            "rate_per_unit": 14.1425,
            "group": "1",
            "calcdate": "07.10.2025"
        },
        {
            "exchangedate": "08.10.2025",
            "r030": 818,
            "cc": "EGP",
            "txt": "Єгипетський фунт",
            "enname": "Egyptian Pound",
            "rate": 0.8688,
            "units": 1,
            "rate_per_unit": 0.8688,
            "group": "1",
            "calcdate": "07.10.2025"
        },
        {
            "exchangedate": "07.10.2025",
            "r030": 818,
            "cc": "EGP",
            "txt": "Єгипетський фунт",
            "enname": "Egyptian Pound",
            "rate": 0.8684,
            "units": 1,
            "rate_per_unit": 0.8684,
            "group": "1",
            "calcdate": "06.10.2025"
        },
        {
            "exchangedate": "08.10.2025",
            "r030": 826,
            "cc": "GBP",
            "txt": "Фунт стерлінгів",
            "enname": "Pound Sterling",
            "rate": 55.3632,
            "units": 1,
            "rate_per_unit": 55.3632,
            "group": "1",
            "calcdate": "07.10.2025"
        },
        {
            "exchangedate": "07.10.2025",
            "r030": 826,
            "cc": "GBP",
            "txt": "Фунт стерлінгів",
            "enname": "Pound Sterling",
            "rate": 55.5064,
            "units": 1,
            "rate_per_unit": 55.5064,
            "group": "1",
            "calcdate": "06.10.2025"
        },
        {
            "exchangedate": "07.10.2025",
            "r030": 840,
            "cc": "USD",
            "txt": "Долар США",
            "enname": "US Dollar",
            "rate": 41.3409,
            "units": 1,
            "rate_per_unit": 41.3409,
            "group": "1",
            "calcdate": "06.10.2025"
        },
        {
            "exchangedate": "08.10.2025",
            "r030": 840,
            "cc": "USD",
            "txt": "Долар США",
            "enname": "US Dollar",
            "rate": 41.3158,
            "units": 1,
            "rate_per_unit": 41.3158,
            "group": "1",
            "calcdate": "07.10.2025"
        },
        {
            "exchangedate": "08.10.2025",
            "r030": 941,
            "cc": "RSD",
            "txt": "Сербський динар",
            "enname": "Serbian Dinar",
            "rate": 4.1115,
            "units": 10,
            "rate_per_unit": 0.41115,
            "group": "1",
            "calcdate": "07.10.2025"
        },
        {
            "exchangedate": "07.10.2025",
            "r030": 941,
            "cc": "RSD",
            "txt": "Сербський динар",
            "enname": "Serbian Dinar",
            "rate": 4.1201,
            "units": 10,
            "rate_per_unit": 0.41201,
            "group": "1",
            "calcdate": "06.10.2025"
        },
        {
            "exchangedate": "07.10.2025",
            "r030": 944,
            "cc": "AZN",
            "txt": "Азербайджанський манат",
            "enname": "Azerbaijan Manat",
            "rate": 24.3153,
            "units": 1,
            "rate_per_unit": 24.3153,
            "group": "1",
            "calcdate": "06.10.2025"
        },
        {
            "exchangedate": "08.10.2025",
            "r030": 944,
            "cc": "AZN",
            "txt": "Азербайджанський манат",
            "enname": "Azerbaijan Manat",
            "rate": 24.3077,
            "units": 1,
            "rate_per_unit": 24.3077,
            "group": "1",
            "calcdate": "07.10.2025"
        },
        {
            "exchangedate": "08.10.2025",
            "r030": 946,
            "cc": "RON",
            "txt": "Румунський лей",
            "enname": "Romanian Leu",
            "rate": 9.46,
            "units": 1,
            "rate_per_unit": 9.46,
            "group": "1",
            "calcdate": "07.10.2025"
        },
        {
            "exchangedate": "07.10.2025",
            "r030": 946,
            "cc": "RON",
            "txt": "Румунський лей",
            "enname": "Romanian Leu",
            "rate": 9.486,
            "units": 1,
            "rate_per_unit": 9.486,
            "group": "1",
            "calcdate": "06.10.2025"
        },
        {
            "exchangedate": "08.10.2025",
            "r030": 949,
            "cc": "TRY",
            "txt": "Турецька ліра",
            "enname": "Turkish Lira",
            "rate": 0.9907,
            "units": 1,
            "rate_per_unit": 0.9907,
            "group": "1",
            "calcdate": "07.10.2025"
        },
        {
            "exchangedate": "07.10.2025",
            "r030": 949,
            "cc": "TRY",
            "txt": "Турецька ліра",
            "enname": "Turkish Lira",
            "rate": 0.9915,
            "units": 1,
            "rate_per_unit": 0.9915,
            "group": "1",
            "calcdate": "06.10.2025"
        },
        {
            "exchangedate": "07.10.2025",
            "r030": 959,
            "cc": "XAU",
            "txt": "Золото",
            "enname": "Gold",
            "rate": 162807.08,
            "units": 1,
            "rate_per_unit": 162807.08,
            "group": "3",
            "calcdate": "06.10.2025"
        },
        {
            "exchangedate": "08.10.2025",
            "r030": 959,
            "cc": "XAU",
            "txt": "Золото",
            "enname": "Gold",
            "rate": 163910.11,
            "units": 1,
            "rate_per_unit": 163910.11,
            "group": "3",
            "calcdate": "07.10.2025"
        },
        {
            "exchangedate": "08.10.2025",
            "r030": 960,
            "cc": "XDR",
            "txt": "СПЗ (спеціальні права запозичення)",
            "enname": "SDR (Special Drawing Right)",
            "rate": 56.4312,
            "units": 1,
            "rate_per_unit": 56.4312,
            "group": "1",
            "calcdate": "07.10.2025"
        },
        {
            "exchangedate": "07.10.2025",
            "r030": 960,
            "cc": "XDR",
            "txt": "СПЗ (спеціальні права запозичення)",
            "enname": "SDR (Special Drawing Right)",
            "rate": 56.5123,
            "units": 1,
            "rate_per_unit": 56.5123,
            "group": "1",
            "calcdate": "06.10.2025"
        },
        {
            "exchangedate": "08.10.2025",
            "r030": 961,
            "cc": "XAG",
            "txt": "Срібло",
            "enname": "Silver",
            "rate": 2008.57,
            "units": 1,
            "rate_per_unit": 2008.57,
            "group": "3",
            "calcdate": "07.10.2025"
        },
        {
            "exchangedate": "07.10.2025",
            "r030": 961,
            "cc": "XAG",
            "txt": "Срібло",
            "enname": "Silver",
            "rate": 2000.68,
            "units": 1,
            "rate_per_unit": 2000.68,
            "group": "3",
            "calcdate": "06.10.2025"
        },
        {
            "exchangedate": "07.10.2025",
            "r030": 962,
            "cc": "XPT",
            "txt": "Платина",
            "enname": "Platinum",
            "rate": 66604.32,
            "units": 1,
            "rate_per_unit": 66604.32,
            "group": "3",
            "calcdate": "06.10.2025"
        },
        {
            "exchangedate": "08.10.2025",
            "r030": 962,
            "cc": "XPT",
            "txt": "Платина",
            "enname": "Platinum",
            "rate": 67435.65,
            "units": 1,
            "rate_per_unit": 67435.65,
            "group": "3",
            "calcdate": "07.10.2025"
        },
        {
            "exchangedate": "08.10.2025",
            "r030": 964,
            "cc": "XPD",
            "txt": "Паладій",
            "enname": "Palladium",
            "rate": 55311.11,
            "units": 1,
            "rate_per_unit": 55311.11,
            "group": "3",
            "calcdate": "07.10.2025"
        },
        {
            "exchangedate": "07.10.2025",
            "r030": 964,
            "cc": "XPD",
            "txt": "Паладій",
            "enname": "Palladium",
            "rate": 52632.34,
            "units": 1,
            "rate_per_unit": 52632.34,
            "group": "3",
            "calcdate": "06.10.2025"
        },
        {
            "exchangedate": "08.10.2025",
            "r030": 975,
            "cc": "BGN",
            "txt": "Болгарський лев",
            "enname": "Bulgarian Lev",
            "rate": 24.6367,
            "units": 1,
            "rate_per_unit": 24.6367,
            "group": "1",
            "calcdate": "07.10.2025"
        },
        {
            "exchangedate": "07.10.2025",
            "r030": 975,
            "cc": "BGN",
            "txt": "Болгарський лев",
            "enname": "Bulgarian Lev",
            "rate": 24.6752,
            "units": 1,
            "rate_per_unit": 24.6752,
            "group": "1",
            "calcdate": "06.10.2025"
        },
        {
            "exchangedate": "07.10.2025",
            "r030": 978,
            "cc": "EUR",
            "txt": "Євро",
            "enname": "Euro",
            "rate": 48.2696,
            "units": 1,
            "rate_per_unit": 48.2696,
            "group": "1",
            "calcdate": "06.10.2025"
        },
        {
            "exchangedate": "08.10.2025",
            "r030": 978,
            "cc": "EUR",
            "txt": "Євро",
            "enname": "Euro",
            "rate": 48.1742,
            "units": 1,
            "rate_per_unit": 48.1742,
            "group": "1",
            "calcdate": "07.10.2025"
        },
        {
            "exchangedate": "07.10.2025",
            "r030": 981,
            "cc": "GEL",
            "txt": "Ларі",
            "enname": "Lari",
            "rate": 15.2128,
            "units": 1,
            "rate_per_unit": 15.2128,
            "group": "1",
            "calcdate": "06.10.2025"
        },
        {
            "exchangedate": "08.10.2025",
            "r030": 981,
            "cc": "GEL",
            "txt": "Ларі",
            "enname": "Lari",
            "rate": 15.2384,
            "units": 1,
            "rate_per_unit": 15.2384,
            "group": "1",
            "calcdate": "07.10.2025"
        },
        {
            "exchangedate": "07.10.2025",
            "r030": 985,
            "cc": "PLN",
            "txt": "Злотий",
            "enname": "Zloty",
            "rate": 11.3505,
            "units": 1,
            "rate_per_unit": 11.3505,
            "group": "1",
            "calcdate": "06.10.2025"
        },
        {
            "exchangedate": "08.10.2025",
            "r030": 985,
            "cc": "PLN",
            "txt": "Злотий",
            "enname": "Zloty",
            "rate": 11.3231,
            "units": 1,
            "rate_per_unit": 11.3231,
            "group": "1",
            "calcdate": "07.10.2025"
        }
    ],
    [
        {
            "exchangedate": "09.10.2025",
            "r030": 12,
            "cc": "DZD",
            "txt": "Алжирський динар",
            "enname": "Algerian Dinar",
            "rate": 3.1915,
            "units": 10,
            "rate_per_unit": 0.31915,
            "group": "1",
            "calcdate": "08.10.2025"
        },
        {
            "exchangedate": "08.10.2025",
            "r030": 12,
            "cc": "DZD",
            "txt": "Алжирський динар",
            "enname": "Algerian Dinar",
            "rate": 3.1888,
            "units": 10,
            "rate_per_unit": 0.31888,
            "group": "1",
            "calcdate": "07.10.2025"
        },
        {
            "exchangedate": "08.10.2025",
            "r030": 36,
            "cc": "AUD",
            "txt": "Австралійський долар",
            "enname": "Australian Dollar",
            "rate": 27.2106,
            "units": 1,
            "rate_per_unit": 27.2106,
            "group": "1",
            "calcdate": "07.10.2025"
        },
        {
            "exchangedate": "09.10.2025",
            "r030": 36,
            "cc": "AUD",
            "txt": "Австралійський долар",
            "enname": "Australian Dollar",
            "rate": 27.2076,
            "units": 1,
            "rate_per_unit": 27.2076,
            "group": "1",
            "calcdate": "08.10.2025"
        },
        {
            "exchangedate": "08.10.2025",
            "r030": 50,
            "cc": "BDT",
            "txt": "Така",
            "enname": "Taka",
            "rate": 3.3986,
            "units": 10,
            "rate_per_unit": 0.33986,
            "group": "1",
            "calcdate": "07.10.2025"
        },
        {
            "exchangedate": "09.10.2025",
            "r030": 50,
            "cc": "BDT",
            "txt": "Така",
            "enname": "Taka",
            "rate": 3.4057,
            "units": 10,
            "rate_per_unit": 0.34057,
            "group": "1",
            "calcdate": "08.10.2025"
        },
        {
            "exchangedate": "08.10.2025",
            "r030": 124,
            "cc": "CAD",
            "txt": "Канадський долар",
            "enname": "Canadian Dollar",
            "rate": 29.598,
            "units": 1,
            "rate_per_unit": 29.598,
            "group": "1",
            "calcdate": "07.10.2025"
        },
        {
            "exchangedate": "09.10.2025",
            "r030": 124,
            "cc": "CAD",
            "txt": "Канадський долар",
            "enname": "Canadian Dollar",
            "rate": 29.6877,
            "units": 1,
            "rate_per_unit": 29.6877,
            "group": "1",
            "calcdate": "08.10.2025"
        },
        {
            "exchangedate": "09.10.2025",
            "r030": 156,
            "cc": "CNY",
            "txt": "Юань Женьміньбі",
            "enname": "Yuan Renminbi ",
            "rate": 5.814,
            "units": 1,
            "rate_per_unit": 5.814,
            "group": "1",
            "calcdate": "08.10.2025"
        },
        {
            "exchangedate": "08.10.2025",
            "r030": 156,
            "cc": "CNY",
            "txt": "Юань Женьміньбі",
            "enname": "Yuan Renminbi ",
            "rate": 5.8018,
            "units": 1,
            "rate_per_unit": 5.8018,
            "group": "1",
            "calcdate": "07.10.2025"
        },
        {
            "exchangedate": "09.10.2025",
            "r030": 203,
            "cc": "CZK",
            "txt": "Чеська крона",
            "enname": "Czech Koruna",
            "rate": 1.9764,
            "units": 1,
            "rate_per_unit": 1.9764,
            "group": "1",
            "calcdate": "08.10.2025"
        },
        {
            "exchangedate": "08.10.2025",
            "r030": 203,
            "cc": "CZK",
            "txt": "Чеська крона",
            "enname": "Czech Koruna",
            "rate": 1.981,
            "units": 1,
            "rate_per_unit": 1.981,
            "group": "1",
            "calcdate": "07.10.2025"
        },
        {
            "exchangedate": "09.10.2025",
            "r030": 208,
            "cc": "DKK",
            "txt": "Данська крона",
            "enname": "Danish Krone",
            "rate": 6.447,
            "units": 1,
            "rate_per_unit": 6.447,
            "group": "1",
            "calcdate": "08.10.2025"
        },
        {
            "exchangedate": "08.10.2025",
            "r030": 208,
            "cc": "DKK",
            "txt": "Данська крона",
            "enname": "Danish Krone",
            "rate": 6.4526,
            "units": 1,
            "rate_per_unit": 6.4526,
            "group": "1",
            "calcdate": "07.10.2025"
        },
        {
            "exchangedate": "08.10.2025",
            "r030": 344,
            "cc": "HKD",
            "txt": "Гонконгівський долар",
            "enname": "Hong Kong Dollar",
            "rate": 5.3084,
            "units": 1,
            "rate_per_unit": 5.3084,
            "group": "1",
            "calcdate": "07.10.2025"
        },
        {
            "exchangedate": "09.10.2025",
            "r030": 344,
            "cc": "HKD",
            "txt": "Гонконгівський долар",
            "enname": "Hong Kong Dollar",
            "rate": 5.3203,
            "units": 1,
            "rate_per_unit": 5.3203,
            "group": "1",
            "calcdate": "08.10.2025"
        },
        {
            "exchangedate": "08.10.2025",
            "r030": 348,
            "cc": "HUF",
            "txt": "Форинт",
            "enname": "Forint",
            "rate": 12.2821,
            "units": 100,
            "rate_per_unit": 0.122821,
            "group": "1",
            "calcdate": "07.10.2025"
        },
        {
            "exchangedate": "09.10.2025",
            "r030": 348,
            "cc": "HUF",
            "txt": "Форинт",
            "enname": "Forint",
            "rate": 12.2667,
            "units": 100,
            "rate_per_unit": 0.122667,
            "group": "1",
            "calcdate": "08.10.2025"
        },
        {
            "exchangedate": "09.10.2025",
            "r030": 356,
            "cc": "INR",
            "txt": "Індійська рупія",
            "enname": "Indian Rupee",
            "rate": 4.6626,
            "units": 10,
            "rate_per_unit": 0.46626,
            "group": "1",
            "calcdate": "08.10.2025"
        },
        {
            "exchangedate": "08.10.2025",
            "r030": 356,
            "cc": "INR",
            "txt": "Індійська рупія",
            "enname": "Indian Rupee",
            "rate": 4.6536,
            "units": 10,
            "rate_per_unit": 0.46536,
            "group": "1",
            "calcdate": "07.10.2025"
        },
        {
            "exchangedate": "09.10.2025",
            "r030": 360,
            "cc": "IDR",
            "txt": "Рупія",
            "enname": "Rupiah",
            "rate": 2.4988,
            "units": 1000,
            "rate_per_unit": 0.0024988,
            "group": "1",
            "calcdate": "08.10.2025"
        },
        {
            "exchangedate": "08.10.2025",
            "r030": 360,
            "cc": "IDR",
            "txt": "Рупія",
            "enname": "Rupiah",
            "rate": 2.496,
            "units": 1000,
            "rate_per_unit": 0.002496,
            "group": "1",
            "calcdate": "07.10.2025"
        },
        {
            "exchangedate": "09.10.2025",
            "r030": 376,
            "cc": "ILS",
            "txt": "Новий ізраїльський шекель",
            "enname": "New Israeli Sheqel",
            "rate": 12.6146,
            "units": 1,
            "rate_per_unit": 12.6146,
            "group": "1",
            "calcdate": "08.10.2025"
        },
        {
            "exchangedate": "08.10.2025",
            "r030": 376,
            "cc": "ILS",
            "txt": "Новий ізраїльський шекель",
            "enname": "New Israeli Sheqel",
            "rate": 12.6101,
            "units": 1,
            "rate_per_unit": 12.6101,
            "group": "1",
            "calcdate": "07.10.2025"
        },
        {
            "exchangedate": "09.10.2025",
            "r030": 392,
            "cc": "JPY",
            "txt": "Єна",
            "enname": "Yen",
            "rate": 2.7115,
            "units": 10,
            "rate_per_unit": 0.27115,
            "group": "1",
            "calcdate": "08.10.2025"
        },
        {
            "exchangedate": "08.10.2025",
            "r030": 392,
            "cc": "JPY",
            "txt": "Єна",
            "enname": "Yen",
            "rate": 2.738,
            "units": 10,
            "rate_per_unit": 0.2738,
            "group": "1",
            "calcdate": "07.10.2025"
        },
        {
            "exchangedate": "08.10.2025",
            "r030": 398,
            "cc": "KZT",
            "txt": "Теньге",
            "enname": "Tenge",
            "rate": 7.6347,
            "units": 100,
            "rate_per_unit": 0.076347,
            "group": "1",
            "calcdate": "07.10.2025"
        },
        {
            "exchangedate": "09.10.2025",
            "r030": 398,
            "cc": "KZT",
            "txt": "Теньге",
            "enname": "Tenge",
            "rate": 7.6595,
            "units": 100,
            "rate_per_unit": 0.076595,
            "group": "1",
            "calcdate": "08.10.2025"
        },
        {
            "exchangedate": "08.10.2025",
            "r030": 410,
            "cc": "KRW",
            "txt": "Вона",
            "enname": "Won",
            "rate": 2.9233,
            "units": 100,
            "rate_per_unit": 0.029233,
            "group": "1",
            "calcdate": "07.10.2025"
        },
        {
            "exchangedate": "09.10.2025",
            "r030": 410,
            "cc": "KRW",
            "txt": "Вона",
            "enname": "Won",
            "rate": 2.9054,
            "units": 100,
            "rate_per_unit": 0.029054,
            "group": "1",
            "calcdate": "08.10.2025"
        },
        {
            "exchangedate": "09.10.2025",
            "r030": 422,
            "cc": "LBP",
            "txt": "Ліванський фунт",
            "enname": "Lebanese Pound",
            "rate": 0.0462,
            "units": 100,
            "rate_per_unit": 0.000462,
            "group": "1",
            "calcdate": "08.10.2025"
        },
        {
            "exchangedate": "08.10.2025",
            "r030": 422,
            "cc": "LBP",
            "txt": "Ліванський фунт",
            "enname": "Lebanese Pound",
            "rate": 0.0461,
            "units": 100,
            "rate_per_unit": 0.000461,
            "group": "1",
            "calcdate": "07.10.2025"
        },
        {
            "exchangedate": "08.10.2025",
            "r030": 458,
            "cc": "MYR",
            "txt": "Малайзійський ринггіт",
            "enname": "Malaysian Ringgit",
            "rate": 9.8039,
            "units": 1,
            "rate_per_unit": 9.8039,
            "group": "1",
            "calcdate": "07.10.2025"
        },
        {
            "exchangedate": "09.10.2025",
            "r030": 458,
            "cc": "MYR",
            "txt": "Малайзійський ринггіт",
            "enname": "Malaysian Ringgit",
            "rate": 9.8215,
            "units": 1,
            "rate_per_unit": 9.8215,
            "group": "1",
            "calcdate": "08.10.2025"
        },
        {
            "exchangedate": "08.10.2025",
            "r030": 484,
            "cc": "MXN",
            "txt": "Мексиканське песо",
            "enname": "Mexican Peso",
            "rate": 2.2475,
            "units": 1,
            "rate_per_unit": 2.2475,
            "group": "1",
            "calcdate": "07.10.2025"
        },
        {
            "exchangedate": "09.10.2025",
            "r030": 484,
            "cc": "MXN",
            "txt": "Мексиканське песо",
            "enname": "Mexican Peso",
            "rate": 2.2496,
            "units": 1,
            "rate_per_unit": 2.2496,
            "group": "1",
            "calcdate": "08.10.2025"
        },
        {
            "exchangedate": "08.10.2025",
            "r030": 498,
            "cc": "MDL",
            "txt": "Молдовський лей",
            "enname": "Moldovan Leu",
            "rate": 2.4782,
            "units": 1,
            "rate_per_unit": 2.4782,
            "group": "1",
            "calcdate": "07.10.2025"
        },
        {
            "exchangedate": "09.10.2025",
            "r030": 498,
            "cc": "MDL",
            "txt": "Молдовський лей",
            "enname": "Moldovan Leu",
            "rate": 2.4834,
            "units": 1,
            "rate_per_unit": 2.4834,
            "group": "1",
            "calcdate": "08.10.2025"
        },
        {
            "exchangedate": "08.10.2025",
            "r030": 554,
            "cc": "NZD",
            "txt": "Новозеландський долар",
            "enname": "New Zealand Dollar",
            "rate": 23.9859,
            "units": 1,
            "rate_per_unit": 23.9859,
            "group": "1",
            "calcdate": "07.10.2025"
        },
        {
            "exchangedate": "09.10.2025",
            "r030": 554,
            "cc": "NZD",
            "txt": "Новозеландський долар",
            "enname": "New Zealand Dollar",
            "rate": 23.9182,
            "units": 1,
            "rate_per_unit": 23.9182,
            "group": "1",
            "calcdate": "08.10.2025"
        },
        {
            "exchangedate": "08.10.2025",
            "r030": 578,
            "cc": "NOK",
            "txt": "Норвезька крона",
            "enname": "Norwegian Krone",
            "rate": 4.1508,
            "units": 1,
            "rate_per_unit": 4.1508,
            "group": "1",
            "calcdate": "07.10.2025"
        },
        {
            "exchangedate": "09.10.2025",
            "r030": 578,
            "cc": "NOK",
            "txt": "Норвезька крона",
            "enname": "Norwegian Krone",
            "rate": 4.1447,
            "units": 1,
            "rate_per_unit": 4.1447,
            "group": "1",
            "calcdate": "08.10.2025"
        },
        {
            "exchangedate": "08.10.2025",
            "r030": 682,
            "cc": "SAR",
            "txt": "Саудівський ріял",
            "enname": "Saudi Riyal",
            "rate": 11.0143,
            "units": 1,
            "rate_per_unit": 11.0143,
            "group": "1",
            "calcdate": "07.10.2025"
        },
        {
            "exchangedate": "09.10.2025",
            "r030": 682,
            "cc": "SAR",
            "txt": "Саудівський ріял",
            "enname": "Saudi Riyal",
            "rate": 11.0374,
            "units": 1,
            "rate_per_unit": 11.0374,
            "group": "1",
            "calcdate": "08.10.2025"
        },
        {
            "exchangedate": "08.10.2025",
            "r030": 702,
            "cc": "SGD",
            "txt": "Сінгапурський долар",
            "enname": "Singapore Dollar",
            "rate": 31.946,
            "units": 1,
            "rate_per_unit": 31.946,
            "group": "1",
            "calcdate": "07.10.2025"
        },
        {
            "exchangedate": "09.10.2025",
            "r030": 702,
            "cc": "SGD",
            "txt": "Сінгапурський долар",
            "enname": "Singapore Dollar",
            "rate": 31.9562,
            "units": 1,
            "rate_per_unit": 31.9562,
            "group": "1",
            "calcdate": "08.10.2025"
        },
        {
            "exchangedate": "09.10.2025",
            "r030": 704,
            "cc": "VND",
            "txt": "Донг",
            "enname": "Dong",
            "rate": 1.5706,
            "units": 1000,
            "rate_per_unit": 0.0015706,
            "group": "1",
            "calcdate": "08.10.2025"
        },
        {
            "exchangedate": "08.10.2025",
            "r030": 704,
            "cc": "VND",
            "txt": "Донг",
            "enname": "Dong",
            "rate": 1.567,
            "units": 1000,
            "rate_per_unit": 0.001567,
            "group": "1",
            "calcdate": "07.10.2025"
        },
        {
            "exchangedate": "08.10.2025",
            "r030": 710,
            "cc": "ZAR",
            "txt": "Ренд",
            "enname": "Rand",
            "rate": 2.4005,
            "units": 1,
            "rate_per_unit": 2.4005,
            "group": "1",
            "calcdate": "07.10.2025"
        },
        {
            "exchangedate": "09.10.2025",
            "r030": 710,
            "cc": "ZAR",
            "txt": "Ренд",
            "enname": "Rand",
            "rate": 2.4089,
            "units": 1,
            "rate_per_unit": 2.4089,
            "group": "1",
            "calcdate": "08.10.2025"
        },
        {
            "exchangedate": "08.10.2025",
            "r030": 752,
            "cc": "SEK",
            "txt": "Шведська крона",
            "enname": "Swedish Krona",
            "rate": 4.3986,
            "units": 1,
            "rate_per_unit": 4.3986,
            "group": "1",
            "calcdate": "07.10.2025"
        },
        {
            "exchangedate": "09.10.2025",
            "r030": 752,
            "cc": "SEK",
            "txt": "Шведська крона",
            "enname": "Swedish Krona",
            "rate": 4.3912,
            "units": 1,
            "rate_per_unit": 4.3912,
            "group": "1",
            "calcdate": "08.10.2025"
        },
        {
            "exchangedate": "08.10.2025",
            "r030": 756,
            "cc": "CHF",
            "txt": "Швейцарський франк",
            "enname": "Swiss Franc",
            "rate": 51.7288,
            "units": 1,
            "rate_per_unit": 51.7288,
            "group": "1",
            "calcdate": "07.10.2025"
        },
        {
            "exchangedate": "09.10.2025",
            "r030": 756,
            "cc": "CHF",
            "txt": "Швейцарський франк",
            "enname": "Swiss Franc",
            "rate": 51.7401,
            "units": 1,
            "rate_per_unit": 51.7401,
            "group": "1",
            "calcdate": "08.10.2025"
        },
        {
            "exchangedate": "09.10.2025",
            "r030": 764,
            "cc": "THB",
            "txt": "Бат",
            "enname": "Baht",
            "rate": 12.7251,
            "units": 10,
            "rate_per_unit": 1.27251,
            "group": "1",
            "calcdate": "08.10.2025"
        },
        {
            "exchangedate": "08.10.2025",
            "r030": 764,
            "cc": "THB",
            "txt": "Бат",
            "enname": "Baht",
            "rate": 12.7063,
            "units": 10,
            "rate_per_unit": 1.27063,
            "group": "1",
            "calcdate": "07.10.2025"
        },
        {
            "exchangedate": "09.10.2025",
            "r030": 784,
            "cc": "AED",
            "txt": "Дирхам ОАЕ",
            "enname": "UAE Dirham",
            "rate": 11.2721,
            "units": 1,
            "rate_per_unit": 11.2721,
            "group": "1",
            "calcdate": "08.10.2025"
        },
        {
            "exchangedate": "08.10.2025",
            "r030": 784,
            "cc": "AED",
            "txt": "Дирхам ОАЕ",
            "enname": "UAE Dirham",
            "rate": 11.2485,
            "units": 1,
            "rate_per_unit": 11.2485,
            "group": "1",
            "calcdate": "07.10.2025"
        },
        {
            "exchangedate": "08.10.2025",
            "r030": 788,
            "cc": "TND",
            "txt": "Туніський динар",
            "enname": "Tunisian Dinar",
            "rate": 14.1425,
            "units": 1,
            "rate_per_unit": 14.1425,
            "group": "1",
            "calcdate": "07.10.2025"
        },
        {
            "exchangedate": "09.10.2025",
            "r030": 788,
            "cc": "TND",
            "txt": "Туніський динар",
            "enname": "Tunisian Dinar",
            "rate": 14.1209,
            "units": 1,
            "rate_per_unit": 14.1209,
            "group": "1",
            "calcdate": "08.10.2025"
        },
        {
            "exchangedate": "08.10.2025",
            "r030": 818,
            "cc": "EGP",
            "txt": "Єгипетський фунт",
            "enname": "Egyptian Pound",
            "rate": 0.8688,
            "units": 1,
            "rate_per_unit": 0.8688,
            "group": "1",
            "calcdate": "07.10.2025"
        },
        {
            "exchangedate": "09.10.2025",
            "r030": 818,
            "cc": "EGP",
            "txt": "Єгипетський фунт",
            "enname": "Egyptian Pound",
            "rate": 0.8708,
            "units": 1,
            "rate_per_unit": 0.8708,
            "group": "1",
            "calcdate": "08.10.2025"
        },
        {
            "exchangedate": "08.10.2025",
            "r030": 826,
            "cc": "GBP",
            "txt": "Фунт стерлінгів",
            "enname": "Pound Sterling",
            "rate": 55.3632,
            "units": 1,
            "rate_per_unit": 55.3632,
            "group": "1",
            "calcdate": "07.10.2025"
        },
        {
            "exchangedate": "09.10.2025",
            "r030": 826,
            "cc": "GBP",
            "txt": "Фунт стерлінгів",
            "enname": "Pound Sterling",
            "rate": 55.5041,
            "units": 1,
            "rate_per_unit": 55.5041,
            "group": "1",
            "calcdate": "08.10.2025"
        },
        {
            "exchangedate": "08.10.2025",
            "r030": 840,
            "cc": "USD",
            "txt": "Долар США",
            "enname": "US Dollar",
            "rate": 41.3158,
            "units": 1,
            "rate_per_unit": 41.3158,
            "group": "1",
            "calcdate": "07.10.2025"
        },
        {
            "exchangedate": "09.10.2025",
            "r030": 840,
            "cc": "USD",
            "txt": "Долар США",
            "enname": "US Dollar",
            "rate": 41.4024,
            "units": 1,
            "rate_per_unit": 41.4024,
            "group": "1",
            "calcdate": "08.10.2025"
        },
        {
            "exchangedate": "08.10.2025",
            "r030": 941,
            "cc": "RSD",
            "txt": "Сербський динар",
            "enname": "Serbian Dinar",
            "rate": 4.1115,
            "units": 10,
            "rate_per_unit": 0.41115,
            "group": "1",
            "calcdate": "07.10.2025"
        },
        {
            "exchangedate": "09.10.2025",
            "r030": 941,
            "cc": "RSD",
            "txt": "Сербський динар",
            "enname": "Serbian Dinar",
            "rate": 4.1086,
            "units": 10,
            "rate_per_unit": 0.41086,
            "group": "1",
            "calcdate": "08.10.2025"
        },
        {
            "exchangedate": "09.10.2025",
            "r030": 944,
            "cc": "AZN",
            "txt": "Азербайджанський манат",
            "enname": "Azerbaijan Manat",
            "rate": 24.3601,
            "units": 1,
            "rate_per_unit": 24.3601,
            "group": "1",
            "calcdate": "08.10.2025"
        },
        {
            "exchangedate": "08.10.2025",
            "r030": 944,
            "cc": "AZN",
            "txt": "Азербайджанський манат",
            "enname": "Azerbaijan Manat",
            "rate": 24.3077,
            "units": 1,
            "rate_per_unit": 24.3077,
            "group": "1",
            "calcdate": "07.10.2025"
        },
        {
            "exchangedate": "08.10.2025",
            "r030": 946,
            "cc": "RON",
            "txt": "Румунський лей",
            "enname": "Romanian Leu",
            "rate": 9.46,
            "units": 1,
            "rate_per_unit": 9.46,
            "group": "1",
            "calcdate": "07.10.2025"
        },
        {
            "exchangedate": "09.10.2025",
            "r030": 946,
            "cc": "RON",
            "txt": "Румунський лей",
            "enname": "Romanian Leu",
            "rate": 9.4461,
            "units": 1,
            "rate_per_unit": 9.4461,
            "group": "1",
            "calcdate": "08.10.2025"
        },
        {
            "exchangedate": "09.10.2025",
            "r030": 949,
            "cc": "TRY",
            "txt": "Турецька ліра",
            "enname": "Turkish Lira",
            "rate": 0.9925,
            "units": 1,
            "rate_per_unit": 0.9925,
            "group": "1",
            "calcdate": "08.10.2025"
        },
        {
            "exchangedate": "08.10.2025",
            "r030": 949,
            "cc": "TRY",
            "txt": "Турецька ліра",
            "enname": "Turkish Lira",
            "rate": 0.9907,
            "units": 1,
            "rate_per_unit": 0.9907,
            "group": "1",
            "calcdate": "07.10.2025"
        },
        {
            "exchangedate": "09.10.2025",
            "r030": 959,
            "cc": "XAU",
            "txt": "Золото",
            "enname": "Gold",
            "rate": 167155.98,
            "units": 1,
            "rate_per_unit": 167155.98,
            "group": "3",
            "calcdate": "08.10.2025"
        },
        {
            "exchangedate": "08.10.2025",
            "r030": 959,
            "cc": "XAU",
            "txt": "Золото",
            "enname": "Gold",
            "rate": 163910.11,
            "units": 1,
            "rate_per_unit": 163910.11,
            "group": "3",
            "calcdate": "07.10.2025"
        },
        {
            "exchangedate": "08.10.2025",
            "r030": 960,
            "cc": "XDR",
            "txt": "СПЗ (спеціальні права запозичення)",
            "enname": "SDR (Special Drawing Right)",
            "rate": 56.4312,
            "units": 1,
            "rate_per_unit": 56.4312,
            "group": "1",
            "calcdate": "07.10.2025"
        },
        {
            "exchangedate": "09.10.2025",
            "r030": 960,
            "cc": "XDR",
            "txt": "СПЗ (спеціальні права запозичення)",
            "enname": "SDR (Special Drawing Right)",
            "rate": 56.4572,
            "units": 1,
            "rate_per_unit": 56.4572,
            "group": "1",
            "calcdate": "08.10.2025"
        },
        {
            "exchangedate": "08.10.2025",
            "r030": 961,
            "cc": "XAG",
            "txt": "Срібло",
            "enname": "Silver",
            "rate": 2008.57,
            "units": 1,
            "rate_per_unit": 2008.57,
            "group": "3",
            "calcdate": "07.10.2025"
        },
        {
            "exchangedate": "09.10.2025",
            "r030": 961,
            "cc": "XAG",
            "txt": "Срібло",
            "enname": "Silver",
            "rate": 2028.31,
            "units": 1,
            "rate_per_unit": 2028.31,
            "group": "3",
            "calcdate": "08.10.2025"
        },
        {
            "exchangedate": "09.10.2025",
            "r030": 962,
            "cc": "XPT",
            "txt": "Платина",
            "enname": "Platinum",
            "rate": 68608.75,
            "units": 1,
            "rate_per_unit": 68608.75,
            "group": "3",
            "calcdate": "08.10.2025"
        },
        {
            "exchangedate": "08.10.2025",
            "r030": 962,
            "cc": "XPT",
            "txt": "Платина",
            "enname": "Platinum",
            "rate": 67435.65,
            "units": 1,
            "rate_per_unit": 67435.65,
            "group": "3",
            "calcdate": "07.10.2025"
        },
        {
            "exchangedate": "09.10.2025",
            "r030": 964,
            "cc": "XPD",
            "txt": "Паладій",
            "enname": "Palladium",
            "rate": 57674.79,
            "units": 1,
            "rate_per_unit": 57674.79,
            "group": "3",
            "calcdate": "08.10.2025"
        },
        {
            "exchangedate": "08.10.2025",
            "r030": 964,
            "cc": "XPD",
            "txt": "Паладій",
            "enname": "Palladium",
            "rate": 55311.11,
            "units": 1,
            "rate_per_unit": 55311.11,
            "group": "3",
            "calcdate": "07.10.2025"
        },
        {
            "exchangedate": "09.10.2025",
            "r030": 975,
            "cc": "BGN",
            "txt": "Болгарський лев",
            "enname": "Bulgarian Lev",
            "rate": 24.6164,
            "units": 1,
            "rate_per_unit": 24.6164,
            "group": "1",
            "calcdate": "08.10.2025"
        },
        {
            "exchangedate": "08.10.2025",
            "r030": 975,
            "cc": "BGN",
            "txt": "Болгарський лев",
            "enname": "Bulgarian Lev",
            "rate": 24.6367,
            "units": 1,
            "rate_per_unit": 24.6367,
            "group": "1",
            "calcdate": "07.10.2025"
        },
        {
            "exchangedate": "09.10.2025",
            "r030": 978,
            "cc": "EUR",
            "txt": "Євро",
            "enname": "Euro",
            "rate": 48.1386,
            "units": 1,
            "rate_per_unit": 48.1386,
            "group": "1",
            "calcdate": "08.10.2025"
        },
        {
            "exchangedate": "08.10.2025",
            "r030": 978,
            "cc": "EUR",
            "txt": "Євро",
            "enname": "Euro",
            "rate": 48.1742,
            "units": 1,
            "rate_per_unit": 48.1742,
            "group": "1",
            "calcdate": "07.10.2025"
        },
        {
            "exchangedate": "09.10.2025",
            "r030": 981,
            "cc": "GEL",
            "txt": "Ларі",
            "enname": "Lari",
            "rate": 15.2737,
            "units": 1,
            "rate_per_unit": 15.2737,
            "group": "1",
            "calcdate": "08.10.2025"
        },
        {
            "exchangedate": "08.10.2025",
            "r030": 981,
            "cc": "GEL",
            "txt": "Ларі",
            "enname": "Lari",
            "rate": 15.2384,
            "units": 1,
            "rate_per_unit": 15.2384,
            "group": "1",
            "calcdate": "07.10.2025"
        },
        {
            "exchangedate": "09.10.2025",
            "r030": 985,
            "cc": "PLN",
            "txt": "Злотий",
            "enname": "Zloty",
            "rate": 11.3245,
            "units": 1,
            "rate_per_unit": 11.3245,
            "group": "1",
            "calcdate": "08.10.2025"
        },
        {
            "exchangedate": "08.10.2025",
            "r030": 985,
            "cc": "PLN",
            "txt": "Злотий",
            "enname": "Zloty",
            "rate": 11.3231,
            "units": 1,
            "rate_per_unit": 11.3231,
            "group": "1",
            "calcdate": "07.10.2025"
        }
    ],
    [
        {
            "exchangedate": "10.10.2025",
            "r030": 12,
            "cc": "DZD",
            "txt": "Алжирський динар",
            "enname": "Algerian Dinar",
            "rate": 3.1964,
            "units": 10,
            "rate_per_unit": 0.31964,
            "group": "1",
            "calcdate": "09.10.2025"
        },
        {
            "exchangedate": "09.10.2025",
            "r030": 12,
            "cc": "DZD",
            "txt": "Алжирський динар",
            "enname": "Algerian Dinar",
            "rate": 3.1915,
            "units": 10,
            "rate_per_unit": 0.31915,
            "group": "1",
            "calcdate": "08.10.2025"
        },
        {
            "exchangedate": "10.10.2025",
            "r030": 36,
            "cc": "AUD",
            "txt": "Австралійський долар",
            "enname": "Australian Dollar",
            "rate": 27.3858,
            "units": 1,
            "rate_per_unit": 27.3858,
            "group": "1",
            "calcdate": "09.10.2025"
        },
        {
            "exchangedate": "09.10.2025",
            "r030": 36,
            "cc": "AUD",
            "txt": "Австралійський долар",
            "enname": "Australian Dollar",
            "rate": 27.2076,
            "units": 1,
            "rate_per_unit": 27.2076,
            "group": "1",
            "calcdate": "08.10.2025"
        },
        {
            "exchangedate": "09.10.2025",
            "r030": 50,
            "cc": "BDT",
            "txt": "Така",
            "enname": "Taka",
            "rate": 3.4057,
            "units": 10,
            "rate_per_unit": 0.34057,
            "group": "1",
            "calcdate": "08.10.2025"
        },
        {
            "exchangedate": "10.10.2025",
            "r030": 50,
            "cc": "BDT",
            "txt": "Така",
            "enname": "Taka",
            "rate": 3.4114,
            "units": 10,
            "rate_per_unit": 0.34114,
            "group": "1",
            "calcdate": "09.10.2025"
        },
        {
            "exchangedate": "10.10.2025",
            "r030": 124,
            "cc": "CAD",
            "txt": "Канадський долар",
            "enname": "Canadian Dollar",
            "rate": 29.7472,
            "units": 1,
            "rate_per_unit": 29.7472,
            "group": "1",
            "calcdate": "09.10.2025"
        },
        {
            "exchangedate": "09.10.2025",
            "r030": 124,
            "cc": "CAD",
            "txt": "Канадський долар",
            "enname": "Canadian Dollar",
            "rate": 29.6877,
            "units": 1,
            "rate_per_unit": 29.6877,
            "group": "1",
            "calcdate": "08.10.2025"
        },
        {
            "exchangedate": "09.10.2025",
            "r030": 156,
            "cc": "CNY",
            "txt": "Юань Женьміньбі",
            "enname": "Yuan Renminbi ",
            "rate": 5.814,
            "units": 1,
            "rate_per_unit": 5.814,
            "group": "1",
            "calcdate": "08.10.2025"
        },
        {
            "exchangedate": "10.10.2025",
            "r030": 156,
            "cc": "CNY",
            "txt": "Юань Женьміньбі",
            "enname": "Yuan Renminbi ",
            "rate": 5.8276,
            "units": 1,
            "rate_per_unit": 5.8276,
            "group": "1",
            "calcdate": "09.10.2025"
        },
        {
            "exchangedate": "09.10.2025",
            "r030": 203,
            "cc": "CZK",
            "txt": "Чеська крона",
            "enname": "Czech Koruna",
            "rate": 1.9764,
            "units": 1,
            "rate_per_unit": 1.9764,
            "group": "1",
            "calcdate": "08.10.2025"
        },
        {
            "exchangedate": "10.10.2025",
            "r030": 203,
            "cc": "CZK",
            "txt": "Чеська крона",
            "enname": "Czech Koruna",
            "rate": 1.9822,
            "units": 1,
            "rate_per_unit": 1.9822,
            "group": "1",
            "calcdate": "09.10.2025"
        },
        {
            "exchangedate": "09.10.2025",
            "r030": 208,
            "cc": "DKK",
            "txt": "Данська крона",
            "enname": "Danish Krone",
            "rate": 6.447,
            "units": 1,
            "rate_per_unit": 6.447,
            "group": "1",
            "calcdate": "08.10.2025"
        },
        {
            "exchangedate": "10.10.2025",
            "r030": 208,
            "cc": "DKK",
            "txt": "Данська крона",
            "enname": "Danish Krone",
            "rate": 6.4559,
            "units": 1,
            "rate_per_unit": 6.4559,
            "group": "1",
            "calcdate": "09.10.2025"
        },
        {
            "exchangedate": "09.10.2025",
            "r030": 344,
            "cc": "HKD",
            "txt": "Гонконгівський долар",
            "enname": "Hong Kong Dollar",
            "rate": 5.3203,
            "units": 1,
            "rate_per_unit": 5.3203,
            "group": "1",
            "calcdate": "08.10.2025"
        },
        {
            "exchangedate": "10.10.2025",
            "r030": 344,
            "cc": "HKD",
            "txt": "Гонконгівський долар",
            "enname": "Hong Kong Dollar",
            "rate": 5.3351,
            "units": 1,
            "rate_per_unit": 5.3351,
            "group": "1",
            "calcdate": "09.10.2025"
        },
        {
            "exchangedate": "10.10.2025",
            "r030": 348,
            "cc": "HUF",
            "txt": "Форинт",
            "enname": "Forint",
            "rate": 12.3299,
            "units": 100,
            "rate_per_unit": 0.123299,
            "group": "1",
            "calcdate": "09.10.2025"
        },
        {
            "exchangedate": "09.10.2025",
            "r030": 348,
            "cc": "HUF",
            "txt": "Форинт",
            "enname": "Forint",
            "rate": 12.2667,
            "units": 100,
            "rate_per_unit": 0.122667,
            "group": "1",
            "calcdate": "08.10.2025"
        },
        {
            "exchangedate": "09.10.2025",
            "r030": 356,
            "cc": "INR",
            "txt": "Індійська рупія",
            "enname": "Indian Rupee",
            "rate": 4.6626,
            "units": 10,
            "rate_per_unit": 0.46626,
            "group": "1",
            "calcdate": "08.10.2025"
        },
        {
            "exchangedate": "10.10.2025",
            "r030": 356,
            "cc": "INR",
            "txt": "Індійська рупія",
            "enname": "Indian Rupee",
            "rate": 4.6746,
            "units": 10,
            "rate_per_unit": 0.46746,
            "group": "1",
            "calcdate": "09.10.2025"
        },
        {
            "exchangedate": "09.10.2025",
            "r030": 360,
            "cc": "IDR",
            "txt": "Рупія",
            "enname": "Rupiah",
            "rate": 2.4988,
            "units": 1000,
            "rate_per_unit": 0.0024988,
            "group": "1",
            "calcdate": "08.10.2025"
        },
        {
            "exchangedate": "10.10.2025",
            "r030": 360,
            "cc": "IDR",
            "txt": "Рупія",
            "enname": "Rupiah",
            "rate": 2.5067,
            "units": 1000,
            "rate_per_unit": 0.0025067,
            "group": "1",
            "calcdate": "09.10.2025"
        },
        {
            "exchangedate": "10.10.2025",
            "r030": 376,
            "cc": "ILS",
            "txt": "Новий ізраїльський шекель",
            "enname": "New Israeli Sheqel",
            "rate": 12.7959,
            "units": 1,
            "rate_per_unit": 12.7959,
            "group": "1",
            "calcdate": "09.10.2025"
        },
        {
            "exchangedate": "09.10.2025",
            "r030": 376,
            "cc": "ILS",
            "txt": "Новий ізраїльський шекель",
            "enname": "New Israeli Sheqel",
            "rate": 12.6146,
            "units": 1,
            "rate_per_unit": 12.6146,
            "group": "1",
            "calcdate": "08.10.2025"
        },
        {
            "exchangedate": "10.10.2025",
            "r030": 392,
            "cc": "JPY",
            "txt": "Єна",
            "enname": "Yen",
            "rate": 2.7162,
            "units": 10,
            "rate_per_unit": 0.27162,
            "group": "1",
            "calcdate": "09.10.2025"
        },
        {
            "exchangedate": "09.10.2025",
            "r030": 392,
            "cc": "JPY",
            "txt": "Єна",
            "enname": "Yen",
            "rate": 2.7115,
            "units": 10,
            "rate_per_unit": 0.27115,
            "group": "1",
            "calcdate": "08.10.2025"
        },
        {
            "exchangedate": "10.10.2025",
            "r030": 398,
            "cc": "KZT",
            "txt": "Теньге",
            "enname": "Tenge",
            "rate": 7.667,
            "units": 100,
            "rate_per_unit": 0.07667,
            "group": "1",
            "calcdate": "09.10.2025"
        },
        {
            "exchangedate": "09.10.2025",
            "r030": 398,
            "cc": "KZT",
            "txt": "Теньге",
            "enname": "Tenge",
            "rate": 7.6595,
            "units": 100,
            "rate_per_unit": 0.076595,
            "group": "1",
            "calcdate": "08.10.2025"
        },
        {
            "exchangedate": "09.10.2025",
            "r030": 410,
            "cc": "KRW",
            "txt": "Вона",
            "enname": "Won",
            "rate": 2.9054,
            "units": 100,
            "rate_per_unit": 0.029054,
            "group": "1",
            "calcdate": "08.10.2025"
        },
        {
            "exchangedate": "10.10.2025",
            "r030": 410,
            "cc": "KRW",
            "txt": "Вона",
            "enname": "Won",
            "rate": 2.9248,
            "units": 100,
            "rate_per_unit": 0.029248,
            "group": "1",
            "calcdate": "09.10.2025"
        },
        {
            "exchangedate": "10.10.2025",
            "r030": 422,
            "cc": "LBP",
            "txt": "Ліванський фунт",
            "enname": "Lebanese Pound",
            "rate": 0.0463,
            "units": 100,
            "rate_per_unit": 0.000463,
            "group": "1",
            "calcdate": "09.10.2025"
        },
        {
            "exchangedate": "09.10.2025",
            "r030": 422,
            "cc": "LBP",
            "txt": "Ліванський фунт",
            "enname": "Lebanese Pound",
            "rate": 0.0462,
            "units": 100,
            "rate_per_unit": 0.000462,
            "group": "1",
            "calcdate": "08.10.2025"
        },
        {
            "exchangedate": "10.10.2025",
            "r030": 458,
            "cc": "MYR",
            "txt": "Малайзійський ринггіт",
            "enname": "Malaysian Ringgit",
            "rate": 9.8426,
            "units": 1,
            "rate_per_unit": 9.8426,
            "group": "1",
            "calcdate": "09.10.2025"
        },
        {
            "exchangedate": "09.10.2025",
            "r030": 458,
            "cc": "MYR",
            "txt": "Малайзійський ринггіт",
            "enname": "Malaysian Ringgit",
            "rate": 9.8215,
            "units": 1,
            "rate_per_unit": 9.8215,
            "group": "1",
            "calcdate": "08.10.2025"
        },
        {
            "exchangedate": "09.10.2025",
            "r030": 484,
            "cc": "MXN",
            "txt": "Мексиканське песо",
            "enname": "Mexican Peso",
            "rate": 2.2496,
            "units": 1,
            "rate_per_unit": 2.2496,
            "group": "1",
            "calcdate": "08.10.2025"
        },
        {
            "exchangedate": "10.10.2025",
            "r030": 484,
            "cc": "MXN",
            "txt": "Мексиканське песо",
            "enname": "Mexican Peso",
            "rate": 2.2662,
            "units": 1,
            "rate_per_unit": 2.2662,
            "group": "1",
            "calcdate": "09.10.2025"
        },
        {
            "exchangedate": "09.10.2025",
            "r030": 498,
            "cc": "MDL",
            "txt": "Молдовський лей",
            "enname": "Moldovan Leu",
            "rate": 2.4834,
            "units": 1,
            "rate_per_unit": 2.4834,
            "group": "1",
            "calcdate": "08.10.2025"
        },
        {
            "exchangedate": "10.10.2025",
            "r030": 498,
            "cc": "MDL",
            "txt": "Молдовський лей",
            "enname": "Moldovan Leu",
            "rate": 2.4646,
            "units": 1,
            "rate_per_unit": 2.4646,
            "group": "1",
            "calcdate": "09.10.2025"
        },
        {
            "exchangedate": "09.10.2025",
            "r030": 554,
            "cc": "NZD",
            "txt": "Новозеландський долар",
            "enname": "New Zealand Dollar",
            "rate": 23.9182,
            "units": 1,
            "rate_per_unit": 23.9182,
            "group": "1",
            "calcdate": "08.10.2025"
        },
        {
            "exchangedate": "10.10.2025",
            "r030": 554,
            "cc": "NZD",
            "txt": "Новозеландський долар",
            "enname": "New Zealand Dollar",
            "rate": 23.9906,
            "units": 1,
            "rate_per_unit": 23.9906,
            "group": "1",
            "calcdate": "09.10.2025"
        },
        {
            "exchangedate": "09.10.2025",
            "r030": 578,
            "cc": "NOK",
            "txt": "Норвезька крона",
            "enname": "Norwegian Krone",
            "rate": 4.1447,
            "units": 1,
            "rate_per_unit": 4.1447,
            "group": "1",
            "calcdate": "08.10.2025"
        },
        {
            "exchangedate": "10.10.2025",
            "r030": 578,
            "cc": "NOK",
            "txt": "Норвезька крона",
            "enname": "Norwegian Krone",
            "rate": 4.1463,
            "units": 1,
            "rate_per_unit": 4.1463,
            "group": "1",
            "calcdate": "09.10.2025"
        },
        {
            "exchangedate": "09.10.2025",
            "r030": 682,
            "cc": "SAR",
            "txt": "Саудівський ріял",
            "enname": "Saudi Riyal",
            "rate": 11.0374,
            "units": 1,
            "rate_per_unit": 11.0374,
            "group": "1",
            "calcdate": "08.10.2025"
        },
        {
            "exchangedate": "10.10.2025",
            "r030": 682,
            "cc": "SAR",
            "txt": "Саудівський ріял",
            "enname": "Saudi Riyal",
            "rate": 11.066,
            "units": 1,
            "rate_per_unit": 11.066,
            "group": "1",
            "calcdate": "09.10.2025"
        },
        {
            "exchangedate": "10.10.2025",
            "r030": 702,
            "cc": "SGD",
            "txt": "Сінгапурський долар",
            "enname": "Singapore Dollar",
            "rate": 32.0289,
            "units": 1,
            "rate_per_unit": 32.0289,
            "group": "1",
            "calcdate": "09.10.2025"
        },
        {
            "exchangedate": "09.10.2025",
            "r030": 702,
            "cc": "SGD",
            "txt": "Сінгапурський долар",
            "enname": "Singapore Dollar",
            "rate": 31.9562,
            "units": 1,
            "rate_per_unit": 31.9562,
            "group": "1",
            "calcdate": "08.10.2025"
        },
        {
            "exchangedate": "10.10.2025",
            "r030": 704,
            "cc": "VND",
            "txt": "Донг",
            "enname": "Dong",
            "rate": 1.5752,
            "units": 1000,
            "rate_per_unit": 0.0015752,
            "group": "1",
            "calcdate": "09.10.2025"
        },
        {
            "exchangedate": "09.10.2025",
            "r030": 704,
            "cc": "VND",
            "txt": "Донг",
            "enname": "Dong",
            "rate": 1.5706,
            "units": 1000,
            "rate_per_unit": 0.0015706,
            "group": "1",
            "calcdate": "08.10.2025"
        },
        {
            "exchangedate": "09.10.2025",
            "r030": 710,
            "cc": "ZAR",
            "txt": "Ренд",
            "enname": "Rand",
            "rate": 2.4089,
            "units": 1,
            "rate_per_unit": 2.4089,
            "group": "1",
            "calcdate": "08.10.2025"
        },
        {
            "exchangedate": "10.10.2025",
            "r030": 710,
            "cc": "ZAR",
            "txt": "Ренд",
            "enname": "Rand",
            "rate": 2.4277,
            "units": 1,
            "rate_per_unit": 2.4277,
            "group": "1",
            "calcdate": "09.10.2025"
        },
        {
            "exchangedate": "09.10.2025",
            "r030": 752,
            "cc": "SEK",
            "txt": "Шведська крона",
            "enname": "Swedish Krona",
            "rate": 4.3912,
            "units": 1,
            "rate_per_unit": 4.3912,
            "group": "1",
            "calcdate": "08.10.2025"
        },
        {
            "exchangedate": "10.10.2025",
            "r030": 752,
            "cc": "SEK",
            "txt": "Шведська крона",
            "enname": "Swedish Krona",
            "rate": 4.3894,
            "units": 1,
            "rate_per_unit": 4.3894,
            "group": "1",
            "calcdate": "09.10.2025"
        },
        {
            "exchangedate": "10.10.2025",
            "r030": 756,
            "cc": "CHF",
            "txt": "Швейцарський франк",
            "enname": "Swiss Franc",
            "rate": 51.805,
            "units": 1,
            "rate_per_unit": 51.805,
            "group": "1",
            "calcdate": "09.10.2025"
        },
        {
            "exchangedate": "09.10.2025",
            "r030": 756,
            "cc": "CHF",
            "txt": "Швейцарський франк",
            "enname": "Swiss Franc",
            "rate": 51.7401,
            "units": 1,
            "rate_per_unit": 51.7401,
            "group": "1",
            "calcdate": "08.10.2025"
        },
        {
            "exchangedate": "09.10.2025",
            "r030": 764,
            "cc": "THB",
            "txt": "Бат",
            "enname": "Baht",
            "rate": 12.7251,
            "units": 10,
            "rate_per_unit": 1.27251,
            "group": "1",
            "calcdate": "08.10.2025"
        },
        {
            "exchangedate": "10.10.2025",
            "r030": 764,
            "cc": "THB",
            "txt": "Бат",
            "enname": "Baht",
            "rate": 12.7406,
            "units": 10,
            "rate_per_unit": 1.27406,
            "group": "1",
            "calcdate": "09.10.2025"
        },
        {
            "exchangedate": "09.10.2025",
            "r030": 784,
            "cc": "AED",
            "txt": "Дирхам ОАЕ",
            "enname": "UAE Dirham",
            "rate": 11.2721,
            "units": 1,
            "rate_per_unit": 11.2721,
            "group": "1",
            "calcdate": "08.10.2025"
        },
        {
            "exchangedate": "10.10.2025",
            "r030": 784,
            "cc": "AED",
            "txt": "Дирхам ОАЕ",
            "enname": "UAE Dirham",
            "rate": 11.3007,
            "units": 1,
            "rate_per_unit": 11.3007,
            "group": "1",
            "calcdate": "09.10.2025"
        },
        {
            "exchangedate": "10.10.2025",
            "r030": 788,
            "cc": "TND",
            "txt": "Туніський динар",
            "enname": "Tunisian Dinar",
            "rate": 14.1471,
            "units": 1,
            "rate_per_unit": 14.1471,
            "group": "1",
            "calcdate": "09.10.2025"
        },
        {
            "exchangedate": "09.10.2025",
            "r030": 788,
            "cc": "TND",
            "txt": "Туніський динар",
            "enname": "Tunisian Dinar",
            "rate": 14.1209,
            "units": 1,
            "rate_per_unit": 14.1209,
            "group": "1",
            "calcdate": "08.10.2025"
        },
        {
            "exchangedate": "10.10.2025",
            "r030": 818,
            "cc": "EGP",
            "txt": "Єгипетський фунт",
            "enname": "Egyptian Pound",
            "rate": 0.8728,
            "units": 1,
            "rate_per_unit": 0.8728,
            "group": "1",
            "calcdate": "09.10.2025"
        },
        {
            "exchangedate": "09.10.2025",
            "r030": 818,
            "cc": "EGP",
            "txt": "Єгипетський фунт",
            "enname": "Egyptian Pound",
            "rate": 0.8708,
            "units": 1,
            "rate_per_unit": 0.8708,
            "group": "1",
            "calcdate": "08.10.2025"
        },
        {
            "exchangedate": "10.10.2025",
            "r030": 826,
            "cc": "GBP",
            "txt": "Фунт стерлінгів",
            "enname": "Pound Sterling",
            "rate": 55.5145,
            "units": 1,
            "rate_per_unit": 55.5145,
            "group": "1",
            "calcdate": "09.10.2025"
        },
        {
            "exchangedate": "09.10.2025",
            "r030": 826,
            "cc": "GBP",
            "txt": "Фунт стерлінгів",
            "enname": "Pound Sterling",
            "rate": 55.5041,
            "units": 1,
            "rate_per_unit": 55.5041,
            "group": "1",
            "calcdate": "08.10.2025"
        },
        {
            "exchangedate": "10.10.2025",
            "r030": 840,
            "cc": "USD",
            "txt": "Долар США",
            "enname": "US Dollar",
            "rate": 41.5062,
            "units": 1,
            "rate_per_unit": 41.5062,
            "group": "1",
            "calcdate": "09.10.2025"
        },
        {
            "exchangedate": "09.10.2025",
            "r030": 840,
            "cc": "USD",
            "txt": "Долар США",
            "enname": "US Dollar",
            "rate": 41.4024,
            "units": 1,
            "rate_per_unit": 41.4024,
            "group": "1",
            "calcdate": "08.10.2025"
        },
        {
            "exchangedate": "09.10.2025",
            "r030": 941,
            "cc": "RSD",
            "txt": "Сербський динар",
            "enname": "Serbian Dinar",
            "rate": 4.1086,
            "units": 10,
            "rate_per_unit": 0.41086,
            "group": "1",
            "calcdate": "08.10.2025"
        },
        {
            "exchangedate": "10.10.2025",
            "r030": 941,
            "cc": "RSD",
            "txt": "Сербський динар",
            "enname": "Serbian Dinar",
            "rate": 4.1147,
            "units": 10,
            "rate_per_unit": 0.41147,
            "group": "1",
            "calcdate": "09.10.2025"
        },
        {
            "exchangedate": "09.10.2025",
            "r030": 944,
            "cc": "AZN",
            "txt": "Азербайджанський манат",
            "enname": "Azerbaijan Manat",
            "rate": 24.3601,
            "units": 1,
            "rate_per_unit": 24.3601,
            "group": "1",
            "calcdate": "08.10.2025"
        },
        {
            "exchangedate": "10.10.2025",
            "r030": 944,
            "cc": "AZN",
            "txt": "Азербайджанський манат",
            "enname": "Azerbaijan Manat",
            "rate": 24.4212,
            "units": 1,
            "rate_per_unit": 24.4212,
            "group": "1",
            "calcdate": "09.10.2025"
        },
        {
            "exchangedate": "10.10.2025",
            "r030": 946,
            "cc": "RON",
            "txt": "Румунський лей",
            "enname": "Romanian Leu",
            "rate": 9.4618,
            "units": 1,
            "rate_per_unit": 9.4618,
            "group": "1",
            "calcdate": "09.10.2025"
        },
        {
            "exchangedate": "09.10.2025",
            "r030": 946,
            "cc": "RON",
            "txt": "Румунський лей",
            "enname": "Romanian Leu",
            "rate": 9.4461,
            "units": 1,
            "rate_per_unit": 9.4461,
            "group": "1",
            "calcdate": "08.10.2025"
        },
        {
            "exchangedate": "10.10.2025",
            "r030": 949,
            "cc": "TRY",
            "txt": "Турецька ліра",
            "enname": "Turkish Lira",
            "rate": 0.9948,
            "units": 1,
            "rate_per_unit": 0.9948,
            "group": "1",
            "calcdate": "09.10.2025"
        },
        {
            "exchangedate": "09.10.2025",
            "r030": 949,
            "cc": "TRY",
            "txt": "Турецька ліра",
            "enname": "Turkish Lira",
            "rate": 0.9925,
            "units": 1,
            "rate_per_unit": 0.9925,
            "group": "1",
            "calcdate": "08.10.2025"
        },
        {
            "exchangedate": "09.10.2025",
            "r030": 959,
            "cc": "XAU",
            "txt": "Золото",
            "enname": "Gold",
            "rate": 167155.98,
            "units": 1,
            "rate_per_unit": 167155.98,
            "group": "3",
            "calcdate": "08.10.2025"
        },
        {
            "exchangedate": "10.10.2025",
            "r030": 959,
            "cc": "XAU",
            "txt": "Золото",
            "enname": "Gold",
            "rate": 167866.43,
            "units": 1,
            "rate_per_unit": 167866.43,
            "group": "3",
            "calcdate": "09.10.2025"
        },
        {
            "exchangedate": "10.10.2025",
            "r030": 960,
            "cc": "XDR",
            "txt": "СПЗ (спеціальні права запозичення)",
            "enname": "SDR (Special Drawing Right)",
            "rate": 56.5642,
            "units": 1,
            "rate_per_unit": 56.5642,
            "group": "1",
            "calcdate": "09.10.2025"
        },
        {
            "exchangedate": "09.10.2025",
            "r030": 960,
            "cc": "XDR",
            "txt": "СПЗ (спеціальні права запозичення)",
            "enname": "SDR (Special Drawing Right)",
            "rate": 56.4572,
            "units": 1,
            "rate_per_unit": 56.4572,
            "group": "1",
            "calcdate": "08.10.2025"
        },
        {
            "exchangedate": "09.10.2025",
            "r030": 961,
            "cc": "XAG",
            "txt": "Срібло",
            "enname": "Silver",
            "rate": 2028.31,
            "units": 1,
            "rate_per_unit": 2028.31,
            "group": "3",
            "calcdate": "08.10.2025"
        },
        {
            "exchangedate": "10.10.2025",
            "r030": 961,
            "cc": "XAG",
            "txt": "Срібло",
            "enname": "Silver",
            "rate": 2062.2,
            "units": 1,
            "rate_per_unit": 2062.2,
            "group": "3",
            "calcdate": "09.10.2025"
        },
        {
            "exchangedate": "09.10.2025",
            "r030": 962,
            "cc": "XPT",
            "txt": "Платина",
            "enname": "Platinum",
            "rate": 68608.75,
            "units": 1,
            "rate_per_unit": 68608.75,
            "group": "3",
            "calcdate": "08.10.2025"
        },
        {
            "exchangedate": "10.10.2025",
            "r030": 962,
            "cc": "XPT",
            "txt": "Платина",
            "enname": "Platinum",
            "rate": 69336.52,
            "units": 1,
            "rate_per_unit": 69336.52,
            "group": "3",
            "calcdate": "09.10.2025"
        },
        {
            "exchangedate": "09.10.2025",
            "r030": 964,
            "cc": "XPD",
            "txt": "Паладій",
            "enname": "Palladium",
            "rate": 57674.79,
            "units": 1,
            "rate_per_unit": 57674.79,
            "group": "3",
            "calcdate": "08.10.2025"
        },
        {
            "exchangedate": "10.10.2025",
            "r030": 964,
            "cc": "XPD",
            "txt": "Паладій",
            "enname": "Palladium",
            "rate": 61103.77,
            "units": 1,
            "rate_per_unit": 61103.77,
            "group": "3",
            "calcdate": "09.10.2025"
        },
        {
            "exchangedate": "10.10.2025",
            "r030": 975,
            "cc": "BGN",
            "txt": "Болгарський лев",
            "enname": "Bulgarian Lev",
            "rate": 24.6503,
            "units": 1,
            "rate_per_unit": 24.6503,
            "group": "1",
            "calcdate": "09.10.2025"
        },
        {
            "exchangedate": "09.10.2025",
            "r030": 975,
            "cc": "BGN",
            "txt": "Болгарський лев",
            "enname": "Bulgarian Lev",
            "rate": 24.6164,
            "units": 1,
            "rate_per_unit": 24.6164,
            "group": "1",
            "calcdate": "08.10.2025"
        },
        {
            "exchangedate": "10.10.2025",
            "r030": 978,
            "cc": "EUR",
            "txt": "Євро",
            "enname": "Euro",
            "rate": 48.2053,
            "units": 1,
            "rate_per_unit": 48.2053,
            "group": "1",
            "calcdate": "09.10.2025"
        },
        {
            "exchangedate": "09.10.2025",
            "r030": 978,
            "cc": "EUR",
            "txt": "Євро",
            "enname": "Euro",
            "rate": 48.1386,
            "units": 1,
            "rate_per_unit": 48.1386,
            "group": "1",
            "calcdate": "08.10.2025"
        },
        {
            "exchangedate": "09.10.2025",
            "r030": 981,
            "cc": "GEL",
            "txt": "Ларі",
            "enname": "Lari",
            "rate": 15.2737,
            "units": 1,
            "rate_per_unit": 15.2737,
            "group": "1",
            "calcdate": "08.10.2025"
        },
        {
            "exchangedate": "10.10.2025",
            "r030": 981,
            "cc": "GEL",
            "txt": "Ларі",
            "enname": "Lari",
            "rate": 15.3114,
            "units": 1,
            "rate_per_unit": 15.3114,
            "group": "1",
            "calcdate": "09.10.2025"
        },
        {
            "exchangedate": "09.10.2025",
            "r030": 985,
            "cc": "PLN",
            "txt": "Злотий",
            "enname": "Zloty",
            "rate": 11.3245,
            "units": 1,
            "rate_per_unit": 11.3245,
            "group": "1",
            "calcdate": "08.10.2025"
        },
        {
            "exchangedate": "10.10.2025",
            "r030": 985,
            "cc": "PLN",
            "txt": "Злотий",
            "enname": "Zloty",
            "rate": 11.3303,
            "units": 1,
            "rate_per_unit": 11.3303,
            "group": "1",
            "calcdate": "09.10.2025"
        }
    ]
]